.gitignore
.gitlab-ci.yml
.readthedocs.yaml
Dockerfile
LICENSE
MANIFEST.in
Makefile
README.md
pyproject.toml
setup.py
PycWB.egg-info/PKG-INFO
PycWB.egg-info/SOURCES.txt
PycWB.egg-info/dependency_links.txt
PycWB.egg-info/requires.txt
PycWB.egg-info/top_level.txt
benchmark/README.md
benchmark/io_performance/README.md
benchmark/io_performance/data_gen.py
benchmark/io_performance/parquet_perf.py
benchmark/io_performance/parquet_read_perf.py
benchmark/io_performance/read_pref.py
benchmark/likelihood/README.md
benchmark/likelihood/data_generator.py
benchmark/likelihood/perf_cuda.py
benchmark/likelihood/performance_test_dpf.py
benchmark/likelihood/performance_test_opt_sky.py
benchmark/likelihood/user_parameters_injection.yaml
benchmark/supercluster/README.md
benchmark/supercluster/generate_data.py
benchmark/supercluster/generate_data_2.py
benchmark/supercluster/performance_supercluster.py
benchmark/supercluster/user_parameters_injection.yaml
bin/pycwb
bin/pycwb_search
bin/pycwb_show
cwb-core/Biorthogonal.cc
cwb-core/Biorthogonal.hh
cwb-core/CMakeLists.txt
cwb-core/Daubechies.cc
cwb-core/Daubechies.hh
cwb-core/FourierCoefficients.icc
cwb-core/Haar.cc
cwb-core/Haar.hh
cwb-core/LineFilter.cc
cwb-core/LineFilter.hh
cwb-core/Makefile
cwb-core/Meyer.cc
cwb-core/Meyer.hh
cwb-core/Symlet.cc
cwb-core/Symlet.hh
cwb-core/SymmArray.cc
cwb-core/SymmArray.hh
cwb-core/SymmArraySSE.cc
cwb-core/SymmArraySSE.hh
cwb-core/SymmObjArray.cc
cwb-core/SymmObjArray.hh
cwb-core/WDM.cc
cwb-core/WDM.hh
cwb-core/WDMOverlap.cc
cwb-core/WDMOverlap.hh
cwb-core/WaveDWT.cc
cwb-core/WaveDWT.hh
cwb-core/Wavelet.cc
cwb-core/Wavelet.hh
cwb-core/alm.hh
cwb-core/build.sh
cwb-core/cluster.cc
cwb-core/cluster.hh
cwb-core/constants.hh
cwb-core/detector.cc
cwb-core/detector.hh
cwb-core/injection.cc
cwb-core/injection.hh
cwb-core/lossy.cc
cwb-core/lossy.hh
cwb-core/monster.cc
cwb-core/monster.hh
cwb-core/netcluster.cc
cwb-core/netcluster.hh
cwb-core/netevent.cc
cwb-core/netevent.hh
cwb-core/netpixel.cc
cwb-core/netpixel.hh
cwb-core/network.cc
cwb-core/network.hh
cwb-core/pycwb.hh
cwb-core/rdfr.cc
cwb-core/rdfr.hh
cwb-core/readframe.cc
cwb-core/readframe.hh
