Metadata-Version: 2.4
Name: PycWB
Version: 0.31.0
Summary: A Python package for coherent gravitational wave burst analysis
Home-page: https://git.ligo.org/yumeng.xu/pycwb
Author-email: The PycWB team <yumeng.xu@ligo.org>
Keywords: ligo,physics,gravity,signal processing,gravitational waves,cwb,coherent wave burst
Requires-Python: >=3.8
License-File: LICENSE
Requires-Dist: matplotlib
Requires-Dist: astropy
Requires-Dist: pyyaml
Requires-Dist: jsonschema
Requires-Dist: watchfiles
Requires-Dist: numpy
Requires-Dist: numba
Requires-Dist: gwpy
Requires-Dist: ligo-segments
Requires-Dist: ligo-gracedb
Requires-Dist: aiohttp
Requires-Dist: pycbc
Requires-Dist: filelock
Requires-Dist: scipy<1.14
Requires-Dist: pillow>=9.0.0
Requires-Dist: click
Requires-Dist: orjson
Requires-Dist: dacite
Requires-Dist: lalsuite>=7.0.0
Requires-Dist: prefect
Requires-Dist: prefect-dask
Requires-Dist: dask
Requires-Dist: dask_jobqueue
Requires-Dist: htcondor
Requires-Dist: psutil
Requires-Dist: memspectrum
Requires-Dist: exceptiongroup>=1.0.0; python_version < "3.11"
Requires-Dist: python-ligo-lw<2.0.0
Requires-Dist: scikit-learn
Requires-Dist: jinja2
Requires-Dist: plotly
Requires-Dist: healpy
Requires-Dist: wdm-wavelet
Requires-Dist: burst-waveform
Dynamic: description
Dynamic: description-content-type
Dynamic: home-page
Dynamic: license-file
Dynamic: requires-dist
